proxy2vpn/__init__.py
proxy2vpn/__main__.py
proxy2vpn/common.py
proxy2vpn/adapters/__init__.py
proxy2vpn/adapters/compose_manager.py
proxy2vpn/adapters/compose_utils.py
proxy2vpn/adapters/compose_validator.py
proxy2vpn/adapters/display_utils.py
proxy2vpn/adapters/docker_ops.py
proxy2vpn/adapters/fleet_commands.py
proxy2vpn/adapters/fleet_manager.py
proxy2vpn/adapters/http_client.py
proxy2vpn/adapters/ip_utils.py
proxy2vpn/adapters/logging_utils.py
proxy2vpn/adapters/monitoring.py
proxy2vpn/adapters/profile_allocator.py
proxy2vpn/adapters/server_manager.py
proxy2vpn/adapters/server_monitor.py
proxy2vpn/adapters/validators.py
proxy2vpn/cli/__init__.py
proxy2vpn/cli/main.py
proxy2vpn/cli/typer_ext.py
proxy2vpn/cli/commands/__init__.py
proxy2vpn/cli/commands/fleet.py
proxy2vpn/cli/commands/profile.py
proxy2vpn/cli/commands/servers.py
proxy2vpn/cli/commands/system.py
proxy2vpn/cli/commands/vpn.py
proxy2vpn/core/__init__.py
proxy2vpn/core/config.py
proxy2vpn/core/models.py
proxy2vpn/core/services/__init__.py
proxy2vpn/core/services/diagnostics.py
proxy2vpn-0.15.0.dist-info/licenses/LICENSE
proxy2vpn-0.15.0.dist-info/METADATA
proxy2vpn-0.15.0.dist-info/WHEEL
proxy2vpn-0.15.0.dist-info/entry_points.txt
proxy2vpn-0.15.0.dist-info/top_level.txt
proxy2vpn-0.15.0.dist-info/RECORD
