Metadata-Version: 2.4
Name: proxy2vpn
Version: 0.15.0
Summary: Proxy2VPN Python utilities
Author-email: Serhii Khalymon <serhii.khalymon@pm.me>
License-Expression: MIT
Keywords: vpn,proxy,utilities
Classifier: Programming Language :: Python :: 3
Classifier: Operating System :: OS Independent
Requires-Python: >=3.10
License-File: LICENSE
Requires-Dist: typer
Requires-Dist: ruamel.yaml
Requires-Dist: docker
Requires-Dist: requests
Requires-Dist: aiohttp
Requires-Dist: filelock
Requires-Dist: psutil
Requires-Dist: pydantic>=2
Dynamic: license-file
